testbench/includes.vh
//timescale
`timescale 1ns/1ps

//Global defines
//`define BHVR 
//`define DFF_BHVR
//`define DECODER_BHVR
`define DATA_WIDTH 8
`define MEMORY_DEPTH 256

//includes
`include "../design/instruction_set.vh"
`include "../design/cpu_defines.vh"

`ifdef BHVR
	`include "../design/BHVR/d_ff_bhvr.v"
	`include "../design/BHVR/jk_ff_bhvr.v"
	`include "../design/BHVR/mux_bhvr.v"
	`include "../design/BHVR/decoder_bhvr.v"
`else //structural
	`include "../design/d_ff.v"
	`include "../design/jk_ff.v"
	`include "../design/mux.v"
	`ifdef DECODER_BHVR
		`include "../design/BHVR/decoder_bhvr.v"
	`else
		`include "../design/decoder.v"
	`endif
`endif

`include "../design/tri_state_buffer.v"
`include "../design/register.v"
`include "../design/counter.v"
`include "../design/BHVR/memory_bhvr.v"
`include "../design/ALU_components.v"
`include "../design/ALU.v"
`include "../design/accumulator.v"
`include "../design/CPU.v"

d_ff.v
module d_ff(clk, reset, D, Q, Q_bar);
	input clk, reset, D;
	output Q, Q_bar;

	assign Q_bar = q_bar;

//edge triggered
	//master stage
	and a1(a, D, ~clk);
	and a2(b, ~clk, ~D);
	nor n1(c,a,d);
	nor n2(d,c,b);

	//slave stage
	and a3(e, c, clk);
	and a4(f, clk, d);

	//reset or gate
	or o1(g, ~reset, e);
	and a5(h, reset, f);

	nor n3(Q, g, q_bar);
	nor n4(q_bar, Q, h);

//level triggered
//	nand u1(Q, A, q_bar);
//	nand u2(q_bar, Q, B);
//	nand u3(A, D, clk);
//	nand u4(B, ~D, clk);

endmodule

jk_ff.v
module jk_ff(clk, reset,J, K, Q, Q_bar);
	input clk, reset;
	input J,K;
	output Q, Q_bar;

	assign a = J & Q_bar;
	assign b = ~K & Q;
	assign c = a | b;

	d_ff dff(.D(c), .Q(Q), .Q_bar(Q_bar), .clk(clk), .reset(reset));

endmodule

testbench/d_ff_tb.v
`include "includes.vh"

module d_ff_tb();
	reg clk, reset, D, J, K;
	wire Q, Q1, Q_bar;

	parameter clk_period = 10;
	integer i;

	d_ff dff(.clk(clk),
					 .reset(reset),
					 .D(D),
					 .Q(Q));

	jk_ff jkff(.clk(clk),.reset(reset),.J(J),.K(K),.Q(Q1),.Q_bar(Q_bar));

	initial begin
		$dumpfile("d_ff_tb.vcd");
		$dumpvars(0,d_ff_tb);
		$printtimescale;

		clk <=0;
		reset <=0;
		D <= 0;
		J <= 0;
		K <= 0;
	end

	initial begin
		forever
			#(clk_period/2) clk = ~clk;
	end

	always #(clk_period*3.87) D = ~D;
	always #(clk_period*16.29) reset = ~reset;

	initial begin
		//for (i = 0; i < 10; i++) begin;
		//	#((i%3)*5) D <= ~D;
		//end
		#1000		$finish();
	end

	initial begin
		for(integer i = 0; i < 32; i = i+1) begin
			#7 {J,K} = i[1:0];
			$display("i = %d\t {J,K,Q,Q1} = {%b,%b,%b,%b}",i,J,K,Q1,Q_bar);
		end
	end

//	initial begin
//		$monitor("Time = %0t \t reset = %b \t D = %b\t Q = %b",$time, reset, D, Q);
//	end

//	always@(D) begin
//		$display("Time = %0t \t D = %b\t Q = %b",$time, D, Q);
//	end

endmodule

dump/d_ff_tb.vcd
$date
	Sun Oct 29 17:03:31 2023
$end
$version
	Icarus Verilog
$end
$timescale
	1ps
$end
$scope module d_ff_tb $end
$var wire 1 ! Q_bar $end
$var wire 1 " Q1 $end
$var wire 1 # Q $end
$var parameter 32 $ clk_period $end
$var reg 1 % D $end
$var reg 1 & J $end
$var reg 1 ' K $end
$var reg 1 ( clk $end
$var reg 1 ) reset $end
$scope module dff $end
$var wire 1 % D $end
$var wire 1 # Q $end
$var wire 1 * Q_bar $end
$var wire 1 + a $end
$var wire 1 , b $end
$var wire 1 - c $end
$var wire 1 ( clk $end
$var wire 1 . d $end
$var wire 1 / e $end
$var wire 1 0 f $end
$var wire 1 1 g $end
$var wire 1 2 h $end
$var wire 1 3 q_bar $end
$var wire 1 ) reset $end
$upscope $end
$scope module jkff $end
$var wire 1 & J $end
$var wire 1 ' K $end
$var wire 1 4 a $end
$var wire 1 5 b $end
$var wire 1 6 c $end
$var wire 1 ( clk $end
$var wire 1 ) reset $end
$var wire 1 ! Q_bar $end
$var wire 1 " Q $end
$scope module dff $end
$var wire 1 6 D $end
$var wire 1 " Q $end
$var wire 1 ! Q_bar $end
$var wire 1 7 a $end
$var wire 1 8 b $end
$var wire 1 9 c $end
$var wire 1 ( clk $end
$var wire 1 : d $end
$var wire 1 ; e $end
$var wire 1 < f $end
$var wire 1 = g $end
$var wire 1 > h $end
$var wire 1 ? q_bar $end
$var wire 1 ) reset $end
$upscope $end
$upscope $end
$scope begin $ivl_for_loop0 $end
$var integer 32 @ i [31:0] $end
$upscope $end
$upscope $end
$enddefinitions $end
$comment Show the parameter values. $end
$dumpall
b1010 $
$end
#0
$dumpvars
b0 @
1?
0>
1=
0<
0;
0:
19
18
07
06
05
04
13
02
11
00
0/
0.
1-
1,
0+
1*
0)
0(
0'
0&
0%
0#
0"
1!
$end
#5000
0,
08
1/
1;
1(
#7000
b1 @
#10000
1,
18
0/
0;
0(
#14000
b10 @
1'
#15000
0,
08
1/
1;
1(
#20000
1,
18
0/
0;
0(
#21000
1:
09
08
17
16
14
b11 @
1&
0'
#25000
0,
07
1/
1<
1(
#28000
b100 @
1'
#30000
1,
17
0/
0<
0(
#35000
0,
07
06
1/
1<
04
1(
b101 @
0&
0'
#38700
1%
#40000
1.
19
0-
0:
1+
18
0/
0<
0(
#42000
b110 @
1'
#45000
0+
08
10
1;
1(
#49000
16
14
b111 @
1&
0'
#50000
1:
09
1+
17
00
0;
0(
#55000
0+
07
10
1<
1(
#56000
b1000 @
1'
#60000
1+
17
00
0<
0(
#63000
19
0:
18
07
06
04
b1001 @
0&
0'
#65000
0+
08
10
1;
1(
#70000
1+
18
00
0;
0(
b1010 @
1'
#75000
0+
08
10
1;
1(
#77000
16
14
b1011 @
1&
0'
#77400
0%
#80000
1-
1:
0.
09
1,
17
00
0;
0(
#84000
b1100 @
1'
#85000
0,
07
1/
1<
1(
#90000
1,
17
0/
0<
0(
#91000
19
0:
18
07
06
04
b1101 @
0&
0'
#95000
0,
08
1/
1;
1(
#98000
b1110 @
1'
#100000
1,
18
0/
0;
0(
#105000
0,
08
16
1/
1;
14
1(
b1111 @
1&
0'
#110000
1:
09
1,
17
0/
0;
0(
#112000
b10000 @
1'
#115000
0,
07
1/
1<
1(
#116100
1%
#119000
06
04
b10001 @
0&
0'
#120000
1.
19
0-
0:
1+
18
0/
0<
0(
#125000
0+
08
10
1;
1(
#126000
b10010 @
1'
#130000
1+
18
00
0;
0(
#133000
1:
09
08
17
16
14
b10011 @
1&
0'
#135000
0+
07
10
1<
1(
#140000
1+
17
00
0<
0(
b10100 @
1'
#145000
0+
07
10
1<
1(
#147000
06
04
b10101 @
0&
0'
#150000
19
0:
1+
18
00
0<
0(
#154000
b10110 @
1'
#154800
1-
0.
1,
0+
0%
#155000
0,
08
1/
1;
1(
#160000
1,
18
0/
0;
0(
#161000
1:
09
08
17
16
14
b10111 @
1&
0'
#162900
01
0=
1)
#165000
15
16
1"
04
0!
0?
0,
11
07
1>
1/
1<
1(
#168000
06
05
b11000 @
1'
#170000
19
0:
1,
01
18
0>
0/
0<
0(
#175000
1!
1?
0"
06
0,
11
08
1=
05
1/
1;
1(
b11001 @
0&
0'
#180000
1,
01
18
0=
0/
0;
0(
#182000
b11010 @
1'
#185000
0,
11
08
1=
1/
1;
1(
#189000
16
14
b11011 @
1&
0'
#190000
1:
09
1,
01
17
0=
0/
0;
0(
#193500
1.
0-
0,
1+
1%
#195000
15
16
1#
1"
04
0*
03
0!
0?
0+
12
07
1>
10
1<
1(
#196000
06
05
b11100 @
1'
#200000
19
0:
1+
02
18
0>
00
0<
0(
#203000
1:
09
08
17
16
15
b11101 @
0&
0'
#205000
0+
12
07
1>
10
1<
1(
#210000
19
0:
18
06
1+
02
07
0>
05
00
0<
0(
b11110 @
1'
#215000
1!
1?
0"
0+
12
08
1=
10
1;
1(
#217000
16
14
b11111 @
1&
0'
#220000
1:
09
1+
02
17
0=
00
0;
0(
#224000
b100000 @
1'
#225000
06
1"
04
0!
0?
0+
12
07
1>
10
1<
1(
#230000
19
0:
1+
02
18
0>
00
0<
0(
#232200
1-
0.
1,
0+
0%
#235000
16
14
1*
13
1!
1?
0#
0"
0,
11
08
1=
1/
1;
1(
#240000
1:
09
1,
01
17
0=
0/
0;
0(
#245000
06
1"
04
0!
0?
0,
11
07
1>
1/
1<
1(
#250000
19
0:
1,
01
18
0>
0/
0<
0(
#255000
16
14
1!
1?
0"
0,
11
08
1=
1/
1;
1(
#260000
1:
09
1,
01
17
0=
0/
0;
0(
#265000
06
1"
04
0!
0?
0,
11
07
1>
1/
1<
1(
#270000
19
0:
1,
01
18
0>
0/
0<
0(
#270900
1.
0-
0,
1+
1%
#275000
16
14
1#
1!
1?
0*
03
0"
0+
12
08
1=
10
1;
1(
#280000
1:
09
1+
02
17
0=
00
0;
0(
#285000
06
1"
04
0!
0?
0+
12
07
1>
10
1<
1(
#290000
19
0:
1+
02
18
0>
00
0<
0(
#295000
16
14
1!
1?
0"
0+
12
08
1=
10
1;
1(
#300000
1:
09
1+
02
17
0=
00
0;
0(
#305000
06
1"
04
0!
0?
0+
12
07
1>
10
1<
1(
#309600
0%
#310000
1-
19
0.
0:
1,
02
18
0>
00
0<
0(
#315000
16
14
1*
13
1!
1?
0#
0"
0,
11
08
1=
1/
1;
1(
#320000
1:
09
1,
01
17
0=
0/
0;
0(
#325000
06
1"
04
0!
0?
0,
11
07
1>
1/
1<
1(
#325800
16
14
1!
1?
0"
1=
0>
0)
#330000
1,
17
0/
0<
0(
#335000
0,
07
1/
1<
1(
#340000
1,
17
0/
0<
0(
#345000
0,
07
1/
1<
1(
#348300
1%
#350000
1.
0-
1+
17
0/
0<
0(
#355000
0+
07
10
1<
1(
#360000
1+
17
00
0<
0(
#365000
0+
07
10
1<
1(
#370000
1+
17
00
0<
0(
#375000
0+
07
10
1<
1(
#380000
1+
17
00
0<
0(
#385000
0+
07
10
1<
1(
#387000
0%
#390000
1-
0.
1,
17
00
0<
0(
#395000
0,
07
1/
1<
1(
#400000
1,
17
0/
0<
0(
#405000
0,
07
1/
1<
1(
#410000
1,
17
0/
0<
0(
#415000
0,
07
1/
1<
1(
#420000
1,
17
0/
0<
0(
#425000
0,
07
1/
1<
1(
#425700
1%
#430000
1.
0-
1+
17
0/
0<
0(
#435000
0+
07
10
1<
1(
#440000
1+
17
00
0<
0(
#445000
0+
07
10
1<
1(
#450000
1+
17
00
0<
0(
#455000
0+
07
10
1<
1(
#460000
1+
17
00
0<
0(
#464400
1-
0.
1,
0+
0%
#465000
0,
07
1/
1<
1(
#470000
1,
17
0/
0<
0(
#475000
0,
07
1/
1<
1(
#480000
1,
17
0/
0<
0(
#485000
0,
07
1/
1<
1(
#488700
06
1"
04
0=
0!
0?
1>
1)
#490000
19
0:
1,
01
18
0>
0/
0<
0(
#495000
16
14
1!
1?
0"
0,
11
08
1=
1/
1;
1(
#500000
1:
09
1,
01
17
0=
0/
0;
0(
#503100
1.
0-
0,
1+
1%
#505000
06
1#
1"
04
0*
03
0!
0?
0+
12
07
1>
10
1<
1(
#510000
19
0:
1+
02
18
0>
00
0<
0(
#515000
16
14
1!
1?
0"
0+
12
08
1=
10
1;
1(
#520000
1:
09
1+
02
17
0=
00
0;
0(
#525000
06
1"
04
0!
0?
0+
12
07
1>
10
1<
1(
#530000
19
0:
1+
02
18
0>
00
0<
0(
#535000
16
14
1!
1?
0"
0+
12
08
1=
10
1;
1(
#540000
1:
09
1+
02
17
0=
00
0;
0(
#541800
1-
0.
1,
0+
0%
#545000
06
1*
13
1"
04
0#
0!
0?
0,
11
07
1>
1/
1<
1(
#550000
19
0:
1,
01
18
0>
0/
0<
0(
#555000
16
14
1!
1?
0"
0,
11
08
1=
1/
1;
1(
#560000
1:
09
1,
01
17
0=
0/
0;
0(
#565000
06
1"
04
0!
0?
0,
11
07
1>
1/
1<
1(
#570000
19
0:
1,
01
18
0>
0/
0<
0(
#575000
16
14
1!
1?
0"
0,
11
08
1=
1/
1;
1(
#580000
1:
09
1,
01
17
0=
0/
0;
0(
#580500
1.
0-
0,
1+
1%
#585000
06
1#
1"
04
0*
03
0!
0?
0+
12
07
1>
10
1<
1(
#590000
19
0:
1+
02
18
0>
00
0<
0(
#595000
16
14
1!
1?
0"
0+
12
08
1=
10
1;
1(
#600000
1:
09
1+
02
17
0=
00
0;
0(
#605000
06
1"
04
0!
0?
0+
12
07
1>
10
1<
1(
#610000
19
0:
1+
02
18
0>
00
0<
0(
#615000
16
14
1!
1?
0"
0+
12
08
1=
10
1;
1(
#619200
0%
#620000
1-
1:
0.
09
1,
02
17
0=
00
0;
0(
#625000
06
1*
13
1"
04
0#
0!
0?
0,
11
07
1>
1/
1<
1(
#630000
19
0:
1,
01
18
0>
0/
0<
0(
#635000
16
14
1!
1?
0"
0,
11
08
1=
1/
1;
1(
#640000
1:
09
1,
01
17
0=
0/
0;
0(
#645000
06
1"
04
0!
0?
0,
11
07
1>
1/
1<
1(
#650000
19
0:
1,
01
18
0>
0/
0<
0(
#651600
1:
09
08
17
16
14
1!
1?
0"
11
1=
0)
#655000
0,
07
1/
1<
1(
#657900
1%
#660000
1.
0-
1+
17
0/
0<
0(
#665000
0+
07
10
1<
1(
#670000
1+
17
00
0<
0(
#675000
0+
07
10
1<
1(
#680000
1+
17
00
0<
0(
#685000
0+
07
10
1<
1(
#690000
1+
17
00
0<
0(
#695000
0+
07
10
1<
1(
#696600
0%
#700000
1-
0.
1,
17
00
0<
0(
#705000
0,
07
1/
1<
1(
#710000
1,
17
0/
0<
0(
#715000
0,
07
1/
1<
1(
#720000
1,
17
0/
0<
0(
#725000
0,
07
1/
1<
1(
#730000
1,
17
0/
0<
0(
#735000
0,
07
1/
1<
1(
#735300
1%
#740000
1.
0-
1+
17
0/
0<
0(
#745000
0+
07
10
1<
1(
#750000
1+
17
00
0<
0(
#755000
0+
07
10
1<
1(
#760000
1+
17
00
0<
0(
#765000
0+
07
10
1<
1(
#770000
1+
17
00
0<
0(
#774000
1-
0.
1,
0+
0%
#775000
0,
07
1/
1<
1(
#780000
1,
17
0/
0<
0(
#785000
0,
07
1/
1<
1(
#790000
1,
17
0/
0<
0(
#795000
0,
07
1/
1<
1(
#800000
1,
17
0/
0<
0(
#805000
0,
07
1/
1<
1(
#810000
1,
17
0/
0<
0(
#812700
1.
0-
0,
1+
1%
#814500
01
0=
1)
#815000
06
1#
1"
04
0*
03
0!
0?
0+
12
07
1>
10
1<
1(
#820000
19
0:
1+
02
18
0>
00
0<
0(
#825000
16
14
1!
1?
0"
0+
12
08
1=
10
1;
1(
#830000
1:
09
1+
02
17
0=
00
0;
0(
#835000
06
1"
04
0!
0?
0+
12
07
1>
10
1<
1(
#840000
19
0:
1+
02
18
0>
00
0<
0(
#845000
16
14
1!
1?
0"
0+
12
08
1=
10
1;
1(
#850000
1:
09
1+
02
17
0=
00
0;
0(
#851400
1-
0.
1,
0+
0%
#855000
06
1*
13
1"
04
0#
0!
0?
0,
11
07
1>
1/
1<
1(
#860000
19
0:
1,
01
18
0>
0/
0<
0(
#865000
16
14
1!
1?
0"
0,
11
08
1=
1/
1;
1(
#870000
1:
09
1,
01
17
0=
0/
0;
0(
#875000
06
1"
04
0!
0?
0,
11
07
1>
1/
1<
1(
#880000
19
0:
1,
01
18
0>
0/
0<
0(
#885000
16
14
1!
1?
0"
0,
11
08
1=
1/
1;
1(
#890000
1:
09
1,
01
17
0=
0/
0;
0(
#890100
1.
0-
0,
1+
1%
#895000
06
1#
1"
04
0*
03
0!
0?
0+
12
07
1>
10
1<
1(
#900000
19
0:
1+
02
18
0>
00
0<
0(
#905000
16
14
1!
1?
0"
0+
12
08
1=
10
1;
1(
#910000
1:
09
1+
02
17
0=
00
0;
0(
#915000
06
1"
04
0!
0?
0+
12
07
1>
10
1<
1(
#920000
19
0:
1+
02
18
0>
00
0<
0(
#925000
16
14
1!
1?
0"
0+
12
08
1=
10
1;
1(
#928800
0%
#930000
1-
1:
0.
09
1,
02
17
0=
00
0;
0(
#935000
06
1*
13
1"
04
0#
0!
0?
0,
11
07
1>
1/
1<
1(
#940000
19
0:
1,
01
18
0>
0/
0<
0(
#945000
16
14
1!
1?
0"
0,
11
08
1=
1/
1;
1(
#950000
1:
09
1,
01
17
0=
0/
0;
0(
#955000
06
1"
04
0!
0?
0,
11
07
1>
1/
1<
1(
#960000
19
0:
1,
01
18
0>
0/
0<
0(
#965000
16
14
1!
1?
0"
0,
11
08
1=
1/
1;
1(
#967500
1%
#970000
1.
1:
0-
09
1+
01
17
0=
0/
0;
0(
#975000
06
1#
1"
04
0*
03
0!
0?
0+
12
07
1>
10
1<
1(
#977400
16
14
1*
13
1!
1?
0#
0"
11
1=
02
0>
0)
#980000
1+
17
00
0<
0(
#985000
0+
07
10
1<
1(
#990000
1+
17
00
0<
0(
#995000
0+
07
10
1<
1(
#1000000
1+
17
00
0<
0(
