testbench/includes.vh
//timescale
`timescale 1ns/1ps

//Global defines
//`define BHVR 
//`define DFF_BHVR
//`define DECODER_BHVR
`define DATA_WIDTH 8
`define MEMORY_DEPTH 256

//includes
`include "../design/instruction_set.vh"
`include "../design/cpu_defines.vh"

`ifdef BHVR
	`include "../design/BHVR/d_ff_bhvr.v"
	`include "../design/BHVR/jk_ff_bhvr.v"
	`include "../design/BHVR/mux_bhvr.v"
	`include "../design/BHVR/decoder_bhvr.v"
`else //structural
	`include "../design/d_ff.v"
	`include "../design/jk_ff.v"
	`include "../design/mux.v"
	`ifdef DECODER_BHVR
		`include "../design/BHVR/decoder_bhvr.v"
	`else
		`include "../design/decoder.v"
	`endif
`endif

`include "../design/tri_state_buffer.v"
`include "../design/register.v"
`include "../design/counter.v"
`include "../design/BHVR/memory_bhvr.v"
`include "../design/ALU_components.v"
`include "../design/ALU.v"
`include "../design/accumulator.v"
`include "../design/CPU.v"

testbench/basic_tb.v
`include "includes.vh"

module basic_tb();
	localparam dump_file = "basic_tb.vcd";
	reg clk, reset;
	reg [`DATA_WIDTH - 1:0] div_ratio;
	wire clk_out;

	parameter clk_period = 10;
	integer i;

	always #(clk_period/2) clk = ~clk;

	//instantiate DUT

	initial begin
		$dumpfile(dump_file);
		$dumpvars(0,basic_tb);
		$timeformat(-9, 2, " ns", 20);

		clk <=0;
		reset <=0;
		div_ratio <= 0;
		$printtimescale;

		#10 reset = 1'b1;
	end


	initial begin
		#100;
		for(i = 0; i < 10; i = i+1) begin
			#100 div_ratio = i;
			//$display("Time = %t, div_ratio = %d",$time, div_ratio);
		end
		$finish();
	end

	initial begin
		$monitor("Time = %0t /t  = %b",$time, div_ratio);
	end

endmodule

testbench/basic_tb.vcd
$date
	Sat Nov 04 15:28:52 2023
$end
$version
	Icarus Verilog
$end
$timescale
	1ps
$end
$scope module basic_tb $end
$var parameter 32 ! clk_period $end
$var parameter 96 " dump_file $end
$var reg 1 # clk $end
$var reg 8 $ div_ratio [7:0] $end
$var reg 1 % reset $end
$var integer 32 & i [31:0] $end
$upscope $end
$enddefinitions $end
$comment Show the parameter values. $end
$dumpall
b11000100110000101110011011010010110001101011111011101000110001000101110011101100110001101100100 "
b1010 !
$end
#0
$dumpvars
bx &
0%
b0 $
0#
$end
#5000
1#
#10000
0#
1%
#15000
1#
#20000
0#
#25000
1#
#30000
0#
#35000
1#
#40000
0#
#45000
1#
#50000
0#
#55000
1#
#60000
0#
#65000
1#
#70000
0#
#75000
1#
#80000
0#
#85000
1#
#90000
0#
#95000
1#
#100000
0#
b0 &
#105000
1#
#110000
0#
#115000
1#
#120000
0#
#125000
1#
#130000
0#
#135000
1#
#140000
0#
#145000
1#
#150000
0#
#155000
1#
#160000
0#
#165000
1#
#170000
0#
#175000
1#
#180000
0#
#185000
1#
#190000
0#
#195000
1#
#200000
0#
b1 &
#205000
1#
#210000
0#
#215000
1#
#220000
0#
#225000
1#
#230000
0#
#235000
1#
#240000
0#
#245000
1#
#250000
0#
#255000
1#
#260000
0#
#265000
1#
#270000
0#
#275000
1#
#280000
0#
#285000
1#
#290000
0#
#295000
1#
#300000
0#
b10 &
b1 $
#305000
1#
#310000
0#
#315000
1#
#320000
0#
#325000
1#
#330000
0#
#335000
1#
#340000
0#
#345000
1#
#350000
0#
#355000
1#
#360000
0#
#365000
1#
#370000
0#
#375000
1#
#380000
0#
#385000
1#
#390000
0#
#395000
1#
#400000
0#
b11 &
b10 $
#405000
1#
#410000
0#
#415000
1#
#420000
0#
#425000
1#
#430000
0#
#435000
1#
#440000
0#
#445000
1#
#450000
0#
#455000
1#
#460000
0#
#465000
1#
#470000
0#
#475000
1#
#480000
0#
#485000
1#
#490000
0#
#495000
1#
#500000
0#
b100 &
b11 $
#505000
1#
#510000
0#
#515000
1#
#520000
0#
#525000
1#
#530000
0#
#535000
1#
#540000
0#
#545000
1#
#550000
0#
#555000
1#
#560000
0#
#565000
1#
#570000
0#
#575000
1#
#580000
0#
#585000
1#
#590000
0#
#595000
1#
#600000
0#
b101 &
b100 $
#605000
1#
#610000
0#
#615000
1#
#620000
0#
#625000
1#
#630000
0#
#635000
1#
#640000
0#
#645000
1#
#650000
0#
#655000
1#
#660000
0#
#665000
1#
#670000
0#
#675000
1#
#680000
0#
#685000
1#
#690000
0#
#695000
1#
#700000
0#
b110 &
b101 $
#705000
1#
#710000
0#
#715000
1#
#720000
0#
#725000
1#
#730000
0#
#735000
1#
#740000
0#
#745000
1#
#750000
0#
#755000
1#
#760000
0#
#765000
1#
#770000
0#
#775000
1#
#780000
0#
#785000
1#
#790000
0#
#795000
1#
#800000
0#
b111 &
b110 $
#805000
1#
#810000
0#
#815000
1#
#820000
0#
#825000
1#
#830000
0#
#835000
1#
#840000
0#
#845000
1#
#850000
0#
#855000
1#
#860000
0#
#865000
1#
#870000
0#
#875000
1#
#880000
0#
#885000
1#
#890000
0#
#895000
1#
#900000
0#
b1000 &
b111 $
#905000
1#
#910000
0#
#915000
1#
#920000
0#
#925000
1#
#930000
0#
#935000
1#
#940000
0#
#945000
1#
#950000
0#
#955000
1#
#960000
0#
#965000
1#
#970000
0#
#975000
1#
#980000
0#
#985000
1#
#990000
0#
#995000
1#
#1000000
0#
b1001 &
b1000 $
#1005000
1#
#1010000
0#
#1015000
1#
#1020000
0#
#1025000
1#
#1030000
0#
#1035000
1#
#1040000
0#
#1045000
1#
#1050000
0#
#1055000
1#
#1060000
0#
#1065000
1#
#1070000
0#
#1075000
1#
#1080000
0#
#1085000
1#
#1090000
0#
#1095000
1#
#1100000
0#
b1010 &
b1001 $
