clk_divider.v
//`include "C:/Users/soura/Documents/Verilog/testing/timescale.v"

module clk_divider(
	input clk_in,
	input reset,
	input [`DATA_WIDTH - 1:0] div_ratio,
	output reg clk_out
);
	
	real clk_in_period=1, clk_out_period=1;
	real t_start;


 	always @(reset) begin
 		if(!reset)	begin
 			clk_out <= 0;
 			t_start <= $time;
 		end
 	end
 
 	//update clk_out_period
 	always @(posedge clk_in) begin
		$display("posedge clk_in!!");
 		clk_in_period <= $time - t_start;
 		clk_out_period <= clk_in_period * (div_ratio +1);
 		t_start <= $time;
 		$display("CLK IN: Period = %f ns, Freq = %f MHz | CLK OUT Period = %f ns, Freq = %f MHz", clk_in_period, 1000/clk_in_period, clk_out_period, 1000/clk_out_period);
 	end
 
 	initial begin
 		$display("CLK IN: Period = %f ns, Freq = %f MHz | CLK OUT Period = %f ns, Freq = %f MHz", clk_in_period, 1000/clk_in_period, clk_out_period, 1000/clk_out_period);
 	end
 
 
 	always begin
 		clk_out = #(clk_out_period/2) 1'b0;
 		clk_out = #(clk_out_period/2) 1'b1;
 	end

endmodule

testbench/clk_divider_tb.v
//`include "C:/Users/soura/Documents/Verilog/testing/design/timescale.v"
`include "../design/timescale.v"

`include "../design/clk_divider.v"

module clk_divider_tb();
	reg clk, reset;
	reg [`DATA_WIDTH - 1:0] div_ratio;
	wire clk_out;

	parameter clk_period = 10;
	integer i;


	always #(clk_period/2) clk = ~clk;

	initial begin
		$dumpfile("clk_divider_tb.vcd");
		$dumpvars(0,clk_divider_tb);
		$timeformat(-9, 2, " ns", 20);

		clk <=0;
		reset <=0;
		div_ratio <= 0;
		$printtimescale;

		#10 reset = 1'b1;
	end

	clk_divider clk_div(
		.clk_in(clk),
		.reset(reset),
		.div_ratio(div_ratio),
		.clk_out(clk_out)
	);



	initial begin
		#100;
		for(i = 0; i < 10; i = i+1) begin
			#100 div_ratio = i;
			$display("Time = %t, div_ratio = %d",$time, div_ratio);
		end
		$finish();
	end

//	initial begin
//		$monitor("Time = %0t /t  = %b",$time, clk_div.div_ratio);
//	end

endmodule

testbench/clk_divider_tb.vcd
$date
	Tue Sep 27 22:37:26 2022
$end
$version
	Icarus Verilog
$end
$timescale
	1ps
$end
$scope module clk_divider_tb $end
$var wire 1 ! clk_out $end
$var parameter 32 " clk_period $end
$var reg 1 # clk $end
$var reg 2 $ div_ratio [-1:0] $end
$var reg 1 % reset $end
$var integer 32 & i [31:0] $end
$scope module clk_div $end
$var wire 1 # clk_in $end
$var wire 2 ' div_ratio [-1:0] $end
$var wire 1 % reset $end
$var reg 1 ! clk_out $end
$var real 1 ( clk_in_period $end
$var real 1 ) clk_out_period $end
$var real 1 * t_start $end
$upscope $end
$upscope $end
$enddefinitions $end
$comment Show the parameter values. $end
$dumpall
b1010 "
$end
#0
$dumpvars
r0 *
r1 )
r1 (
b0 '
bx &
0%
b0 $
0#
0!
$end
#1000
1!
#1500
0!
#2000
1!
#2500
0!
#3000
1!
#3500
0!
#4000
1!
#4500
0!
#5000
r5 *
r5 (
1!
1#
#5500
0!
#6000
1!
#6500
0!
#7000
1!
#7500
0!
#8000
1!
#8500
0!
#9000
1!
#9500
0!
#10000
1!
0#
1%
#10500
0!
#11000
1!
#11500
0!
#12000
1!
#12500
0!
#13000
1!
#13500
0!
#14000
1!
#14500
0!
#15000
r15 *
r5 )
r10 (
1!
1#
#15500
0!
#18000
1!
#20000
0#
#20500
0!
#23000
1!
#25000
r25 *
r10 )
1#
#25500
0!
#30000
0#
#30500
1!
#35000
r35 *
1#
#35500
0!
#40000
0#
#40500
1!
#45000
r45 *
1#
#45500
0!
#50000
0#
#50500
1!
#55000
r55 *
1#
#55500
0!
#60000
0#
#60500
1!
#65000
r65 *
1#
#65500
0!
#70000
0#
#70500
1!
#75000
r75 *
1#
#75500
0!
#80000
0#
#80500
1!
#85000
r85 *
1#
#85500
0!
#90000
0#
#90500
1!
#95000
r95 *
1#
#95500
0!
#100000
0#
b0 &
#100500
1!
#105000
r105 *
1#
#105500
0!
#110000
0#
#110500
1!
#115000
r115 *
1#
#115500
0!
#120000
0#
#120500
1!
#125000
r125 *
1#
#125500
0!
#130000
0#
#130500
1!
#135000
r135 *
1#
#135500
0!
#140000
0#
#140500
1!
#145000
r145 *
1#
#145500
0!
#150000
0#
#150500
1!
#155000
r155 *
1#
#155500
0!
#160000
0#
#160500
1!
#165000
r165 *
1#
#165500
0!
#170000
0#
#170500
1!
#175000
r175 *
1#
#175500
0!
#180000
0#
#180500
1!
#185000
r185 *
1#
#185500
0!
#190000
0#
#190500
1!
#195000
r195 *
1#
#195500
0!
#200000
0#
b1 &
#200500
1!
#205000
r205 *
1#
#205500
0!
#210000
0#
#210500
1!
#215000
r215 *
1#
#215500
0!
#220000
0#
#220500
1!
#225000
r225 *
1#
#225500
0!
#230000
0#
#230500
1!
#235000
r235 *
1#
#235500
0!
#240000
0#
#240500
1!
#245000
r245 *
1#
#245500
0!
#250000
0#
#250500
1!
#255000
r255 *
1#
#255500
0!
#260000
0#
#260500
1!
#265000
r265 *
1#
#265500
0!
#270000
0#
#270500
1!
#275000
r275 *
1#
#275500
0!
#280000
0#
#280500
1!
#285000
r285 *
1#
#285500
0!
#290000
0#
#290500
1!
#295000
r295 *
1#
#295500
0!
#300000
0#
b10 &
b1 $
b1 '
#300500
1!
#305000
r305 *
r20 )
1#
#305500
0!
#310000
0#
#315000
r315 *
1#
#315500
1!
#320000
0#
#325000
r325 *
1#
#325500
0!
#330000
0#
#335000
r335 *
1#
#335500
1!
#340000
0#
#345000
r345 *
1#
#345500
0!
#350000
0#
#355000
r355 *
1#
#355500
1!
#360000
0#
#365000
r365 *
1#
#365500
0!
#370000
0#
#375000
r375 *
1#
#375500
1!
#380000
0#
#385000
r385 *
1#
#385500
0!
#390000
0#
#395000
r395 *
1#
#395500
1!
#400000
0#
b11 &
b10 $
b10 '
#405000
r405 *
r30 )
1#
#405500
0!
#410000
0#
#415000
r415 *
1#
#420000
0#
#420500
1!
#425000
r425 *
1#
#430000
0#
#435000
r435 *
1#
#435500
0!
#440000
0#
#445000
r445 *
1#
#450000
0#
#450500
1!
#455000
r455 *
1#
#460000
0#
#465000
r465 *
1#
#465500
0!
#470000
0#
#475000
r475 *
1#
#480000
0#
#480500
1!
#485000
r485 *
1#
#490000
0#
#495000
r495 *
1#
#495500
0!
#500000
0#
b100 &
b11 $
b11 '
#505000
r505 *
r40 )
1#
#510000
0#
#510500
1!
#515000
r515 *
1#
#520000
0#
#525000
r525 *
1#
#530000
0#
#530500
0!
#535000
r535 *
1#
#540000
0#
#545000
r545 *
1#
#550000
0#
#550500
1!
#555000
r555 *
1#
#560000
0#
#565000
r565 *
1#
#570000
0#
#570500
0!
#575000
r575 *
1#
#580000
0#
#585000
r585 *
1#
#590000
0#
#590500
1!
#595000
r595 *
1#
#600000
0#
b101 &
b0 $
b0 '
#605000
r605 *
r10 )
1#
#610000
0#
#610500
0!
#615000
r615 *
1#
#615500
1!
#620000
0#
#620500
0!
#625000
r625 *
1#
#625500
1!
#630000
0#
#630500
0!
#635000
r635 *
1#
#635500
1!
#640000
0#
#640500
0!
#645000
r645 *
1#
#645500
1!
#650000
0#
#650500
0!
#655000
r655 *
1#
#655500
1!
#660000
0#
#660500
0!
#665000
r665 *
1#
#665500
1!
#670000
0#
#670500
0!
#675000
r675 *
1#
#675500
1!
#680000
0#
#680500
0!
#685000
r685 *
1#
#685500
1!
#690000
0#
#690500
0!
#695000
r695 *
1#
#695500
1!
#700000
0#
b110 &
b1 $
b1 '
#700500
0!
#705000
r705 *
r20 )
1#
#705500
1!
#710000
0#
#715000
r715 *
1#
#715500
0!
#720000
0#
#725000
r725 *
1#
#725500
1!
#730000
0#
#735000
r735 *
1#
#735500
0!
#740000
0#
#745000
r745 *
1#
#745500
1!
#750000
0#
#755000
r755 *
1#
#755500
0!
#760000
0#
#765000
r765 *
1#
#765500
1!
#770000
0#
#775000
r775 *
1#
#775500
0!
#780000
0#
#785000
r785 *
1#
#785500
1!
#790000
0#
#795000
r795 *
1#
#795500
0!
#800000
0#
b111 &
b10 $
b10 '
#805000
r805 *
r30 )
1#
#805500
1!
#810000
0#
#815000
r815 *
1#
#820000
0#
#820500
0!
#825000
r825 *
1#
#830000
0#
#835000
r835 *
1#
#835500
1!
#840000
0#
#845000
r845 *
1#
#850000
0#
#850500
0!
#855000
r855 *
1#
#860000
0#
#865000
r865 *
1#
#865500
1!
#870000
0#
#875000
r875 *
1#
#880000
0#
#880500
0!
#885000
r885 *
1#
#890000
0#
#895000
r895 *
1#
#895500
1!
#900000
0#
b1000 &
b11 $
b11 '
#905000
r905 *
r40 )
1#
#910000
0#
#910500
0!
#915000
r915 *
1#
#920000
0#
#925000
r925 *
1#
#930000
0#
#930500
1!
#935000
r935 *
1#
#940000
0#
#945000
r945 *
1#
#950000
0#
#950500
0!
#955000
r955 *
1#
#960000
0#
#965000
r965 *
1#
#970000
0#
#970500
1!
#975000
r975 *
1#
#980000
0#
#985000
r985 *
1#
#990000
0#
#990500
0!
#995000
r995 *
1#
#1000000
0#
b1001 &
b0 $
b0 '
#1005000
r1005 *
r10 )
1#
#1010000
0#
#1010500
1!
#1015000
r1015 *
1#
#1015500
0!
#1020000
0#
#1020500
1!
#1025000
r1025 *
1#
#1025500
0!
#1030000
0#
#1030500
1!
#1035000
r1035 *
1#
#1035500
0!
#1040000
0#
#1040500
1!
#1045000
r1045 *
1#
#1045500
0!
#1050000
0#
#1050500
1!
#1055000
r1055 *
1#
#1055500
0!
#1060000
0#
#1060500
1!
#1065000
r1065 *
1#
#1065500
0!
#1070000
0#
#1070500
1!
#1075000
r1075 *
1#
#1075500
0!
#1080000
0#
#1080500
1!
#1085000
r1085 *
1#
#1085500
0!
#1090000
0#
#1090500
1!
#1095000
r1095 *
1#
#1095500
0!
#1100000
0#
b1010 &
b1 $
b1 '
