testbench/includes.v
//`define BHVR

`ifdef BHVR
	`include "../d_ff_bhvr.v"
	`include "../jk_ff_bhvr.v"

`else //structural
	`include "../d_ff.v"
	`include "../jk_ff.v"

`endif

d_ff.v
module d_ff(clk, reset, D, Q, Q_bar);
	input clk, reset, D;
	output Q, Q_bar;

	assign Q_bar = q_bar;

//edge triggered
	//master stage
	and a1(a, D, ~clk);
	and a2(b, ~clk, ~D);
	nor n1(c,a,d);
	nor n2(d,c,b);

	//slave stage
	and a3(e, c, clk);
	and a4(f, clk, d);

	//reset or gate
	or o1(g, ~reset, e);
	and a5(h, reset, f);

	nor n3(Q, g, q_bar);
	nor n4(q_bar, Q, h);

//level triggered
//	nand u1(Q, A, q_bar);
//	nand u2(q_bar, Q, B);
//	nand u3(A, D, clk);
//	nand u4(B, ~D, clk);

endmodule

jk_ff.v
module jk_ff(clk, reset,J, K, Q, Q_bar);
	input clk, reset;
	input J,K;
	output Q, Q_bar;

	assign a = J & Q_bar;
	assign b = ~K & Q;
	assign c = a | b;

	d_ff dff(.D(c), .Q(Q), .Q_bar(Q_bar), .clk(clk), .reset(reset));

endmodule

testbench/d_ff_tb.v
`include "includes.v"

module d_ff_tb();
	reg clk, reset, D, J, K;
	wire Q;

	parameter clk_period = 10;

	always #(clk_period/2) clk = ~clk;

	d_ff dff(.clk(clk),
					 .reset(reset),
					 .D(D),
					 .Q(Q));

	jk_ff jkff(.clk(clk), .reset(reset), .J(J), .K(K), .Q(q), .Q_bar(q_bar));

	initial begin
		$dumpfile("d_ff_tb.vcd");
		$dumpvars(0,d_ff_tb);
		$printtimescale;

		clk <= 0;
		reset <= 1;
		D <= 0;
		J <= 0;
		K <= 0;

		#500 $finish();
	end

	always #(6) D = ~D;
	always #(134) reset = ~reset;

	initial begin
		for(integer i = 0; i < 32; i=i+1) begin
			#7 {J,K} = i[1:0];
			$display("%b,%b|%b,%b", J, K, jkff.Q, jkff.Q_bar);
		end
	end

endmodule

testbench/d_ff_tb.vcd
$date
	Sat Jul 17 17:45:25 2021
$end
$version
	Icarus Verilog
$end
$timescale
	1s
$end
$scope module d_ff_tb $end
$var wire 1 ! q_bar $end
$var wire 1 " q $end
$var wire 1 # Q $end
$var reg 1 $ D $end
$var reg 1 % J $end
$var reg 1 & K $end
$var reg 1 ' clk $end
$var reg 1 ( reset $end
$scope module dff $end
$var wire 1 $ D $end
$var wire 1 # Q $end
$var wire 1 ) Q_bar $end
$var wire 1 * a $end
$var wire 1 + b $end
$var wire 1 , c $end
$var wire 1 ' clk $end
$var wire 1 - d $end
$var wire 1 . e $end
$var wire 1 / f $end
$var wire 1 0 g $end
$var wire 1 1 h $end
$var wire 1 2 q_bar $end
$var wire 1 ( reset $end
$upscope $end
$scope module jkff $end
$var wire 1 % J $end
$var wire 1 & K $end
$var wire 1 3 a $end
$var wire 1 4 b $end
$var wire 1 5 c $end
$var wire 1 ' clk $end
$var wire 1 ( reset $end
$var wire 1 ! Q_bar $end
$var wire 1 " Q $end
$scope module dff $end
$var wire 1 5 D $end
$var wire 1 " Q $end
$var wire 1 ! Q_bar $end
$var wire 1 6 a $end
$var wire 1 7 b $end
$var wire 1 8 c $end
$var wire 1 ' clk $end
$var wire 1 9 d $end
$var wire 1 : e $end
$var wire 1 ; f $end
$var wire 1 < g $end
$var wire 1 = h $end
$var wire 1 > q_bar $end
$var wire 1 ( reset $end
$upscope $end
$upscope $end
$scope begin $ivl_for_loop0 $end
$var integer 32 ? i [31:0] $end
$upscope $end
$upscope $end
$enddefinitions $end
#0
$dumpvars
b0 ?
x>
0=
0<
0;
0:
x9
x8
x7
x6
x5
x4
03
x2
01
00
0/
0.
0-
1,
1+
0*
x)
1(
0'
0&
0%
0$
x#
x"
x!
$end
#5
1)
12
0#
0+
10
06
07
x<
x=
1.
x:
x;
1'
#6
1$
#7
b1 ?
#10
1-
0,
1*
00
x6
x7
0<
0=
0.
0:
0;
0'
#12
1,
0-
1+
0*
0$
#14
18
09
17
06
05
04
b10 ?
1&
#15
1!
1>
0"
0+
10
07
1<
1.
1:
1'
#18
1$
#20
1-
0,
1*
00
17
0<
0.
0:
0'
#21
19
08
07
16
15
13
b11 ?
1%
0&
#24
1,
0-
1+
0*
0$
#25
14
15
1"
03
0!
0>
0+
10
06
1=
1.
1;
1'
#28
05
04
b100 ?
1&
#30
1-
18
0,
09
1*
00
17
0=
0.
0;
0'
1$
#35
1#
1!
1>
0)
02
0"
05
0*
11
07
1<
04
1/
1:
1'
b101 ?
0%
0&
#36
0$
#40
1,
0-
1+
01
17
0<
0/
0:
0'
#42
1-
0,
0+
1*
1$
b110 ?
1&
#45
0*
11
07
1<
1/
1:
1'
#48
0$
#49
15
13
b111 ?
1%
0&
#50
1,
19
0-
08
1+
01
16
0<
0/
0:
0'
#54
1-
0,
0+
1*
1$
#55
14
15
1"
03
0!
0>
0*
11
06
1=
1/
1;
1'
#56
05
04
b1000 ?
1&
#60
18
1,
09
0-
01
17
0=
1+
0/
0;
0'
0$
#63
19
08
07
16
15
14
b1001 ?
0%
0&
#65
1)
12
0#
0+
10
06
1=
1.
1;
1'
#66
1$
#70
18
09
17
1-
0,
05
1*
00
06
0=
04
0.
0;
0'
b1010 ?
1&
#72
1,
0-
1+
0*
0$
#75
1!
1>
0"
0+
10
07
1<
1.
1:
1'
#77
15
13
b1011 ?
1%
0&
#78
1$
#80
1-
19
0,
08
1*
00
16
0<
0.
0:
0'
#84
1,
0-
1+
0*
0$
b1100 ?
1&
#85
05
1"
03
0!
0>
0+
10
06
1=
1.
1;
1'
#90
1-
18
0,
09
1*
00
17
0=
0.
0;
0'
1$
#91
19
08
07
16
15
14
b1101 ?
0%
0&
#95
1#
0)
02
0*
11
06
1=
1/
1;
1'
#96
0$
#98
05
04
b1110 ?
1&
#100
1,
18
0-
09
1+
01
17
0=
0/
0;
0'
#102
1-
0,
0+
1*
1$
#105
13
1!
1>
0"
15
0*
11
07
1<
04
1/
1:
1'
b1111 ?
1%
0&
#108
0$
#110
1,
19
0-
08
1+
01
16
0<
0/
0:
0'
#112
b10000 ?
1&
#114
1-
0,
0+
1*
1$
#115
05
1"
03
0!
0>
0*
11
06
1=
1/
1;
1'
#119
15
14
b10001 ?
0%
0&
#120
1,
0-
01
16
0=
1+
0/
0;
0'
0$
#125
1)
12
0#
0+
10
06
1=
1.
1;
1'
#126
05
04
1$
b10010 ?
1&
#130
1-
18
0,
09
1*
00
17
0=
0.
0;
0'
#132
1,
0-
1+
0*
0$
#133
19
08
07
16
15
14
b10011 ?
1%
0&
#134
19
07
16
13
15
1!
1>
04
0"
10
1<
0(
#135
0+
06
1.
1;
1'
#138
1$
#140
1-
0,
1*
16
0.
0;
0'
b10100 ?
1&
#144
1,
0-
1+
0*
0$
#145
0+
06
1.
1;
1'
#147
05
03
b10101 ?
0%
0&
#150
1-
18
0,
09
1*
17
0.
0;
0'
1$
#154
b10110 ?
1&
#155
0*
07
1/
1:
1'
#156
0$
#160
1,
0-
1+
17
0/
0:
0'
#161
19
08
07
16
15
13
b10111 ?
1%
0&
#162
1-
0,
0+
1*
1$
#165
0*
06
1/
1;
1'
#168
0$
b11000 ?
1&
#170
1,
0-
1+
16
0/
0;
0'
#174
1-
0,
0+
1*
1$
#175
0*
06
05
1/
1;
03
1'
b11001 ?
0%
0&
#180
18
1,
09
0-
17
1+
0/
0;
0'
0$
#182
b11010 ?
1&
#185
0+
07
1.
1:
1'
#186
1$
#189
15
13
b11011 ?
1%
0&
#190
1-
19
0,
08
1*
16
0.
0:
0'
#192
1,
0-
1+
0*
0$
#195
0+
06
1.
1;
1'
#196
b11100 ?
1&
#198
1$
#200
1-
0,
1*
16
0.
0;
0'
#203
18
09
17
06
05
03
b11101 ?
0%
0&
#204
1,
0-
1+
0*
0$
#205
0+
07
1.
1:
1'
#210
1-
0,
1*
17
0.
0:
0'
1$
b11110 ?
1&
#215
0*
07
1/
1:
1'
#216
0$
#217
15
13
b11111 ?
1%
0&
#220
1,
19
0-
08
1+
16
0/
0:
0'
#222
1-
0,
0+
1*
1$
#224
b100000 ?
1&
#225
0*
06
1/
1;
1'
#228
0$
#230
1,
0-
1+
16
0/
0;
0'
#234
1-
0,
0+
1*
1$
#235
0*
06
1/
1;
1'
#240
1,
0-
16
1+
0/
0;
0'
0$
#245
0+
06
1.
1;
1'
#246
1$
#250
1-
0,
1*
16
0.
0;
0'
#252
1,
0-
1+
0*
0$
#255
0+
06
1.
1;
1'
#258
1$
#260
1-
0,
1*
16
0.
0;
0'
#264
1,
0-
1+
0*
0$
#265
0+
06
1.
1;
1'
#268
05
1"
03
0<
0!
0>
1=
1(
#270
1-
18
0,
09
1*
00
17
0=
0.
0;
0'
1$
#275
15
13
1#
1!
1>
0)
02
0"
0*
11
07
1<
1/
1:
1'
#276
0$
#280
1,
19
0-
08
1+
01
16
0<
0/
0:
0'
#282
1-
0,
0+
1*
1$
#285
05
1"
03
0!
0>
0*
11
06
1=
1/
1;
1'
#288
0$
#290
1,
18
0-
09
1+
01
17
0=
0/
0;
0'
#294
1-
0,
0+
1*
1$
#295
15
13
1!
1>
0"
0*
11
07
1<
1/
1:
1'
#300
19
1,
08
0-
01
16
0<
1+
0/
0:
0'
0$
#305
05
1)
12
1"
03
0#
0!
0>
0+
10
06
1=
1.
1;
1'
#306
1$
#310
1-
18
0,
09
1*
00
17
0=
0.
0;
0'
#312
1,
0-
1+
0*
0$
#315
15
13
1!
1>
0"
0+
10
07
1<
1.
1:
1'
#318
1$
#320
1-
19
0,
08
1*
00
16
0<
0.
0:
0'
#324
1,
0-
1+
0*
0$
#325
05
1"
03
0!
0>
0+
10
06
1=
1.
1;
1'
#330
1-
18
0,
09
1*
00
17
0=
0.
0;
0'
1$
#335
15
13
1#
1!
1>
0)
02
0"
0*
11
07
1<
1/
1:
1'
#336
0$
#340
1,
19
0-
08
1+
01
16
0<
0/
0:
0'
#342
1-
0,
0+
1*
1$
#345
05
1"
03
0!
0>
0*
11
06
1=
1/
1;
1'
#348
0$
#350
1,
18
0-
09
1+
01
17
0=
0/
0;
0'
#354
1-
0,
0+
1*
1$
#355
15
13
1!
1>
0"
0*
11
07
1<
1/
1:
1'
#360
19
1,
08
0-
01
16
0<
1+
0/
0:
0'
0$
#365
05
1)
12
1"
03
0#
0!
0>
0+
10
06
1=
1.
1;
1'
#366
1$
#370
1-
18
0,
09
1*
00
17
0=
0.
0;
0'
#372
1,
0-
1+
0*
0$
#375
15
13
1!
1>
0"
0+
10
07
1<
1.
1:
1'
#378
1$
#380
1-
19
0,
08
1*
00
16
0<
0.
0:
0'
#384
1,
0-
1+
0*
0$
#385
05
1"
03
0!
0>
0+
10
06
1=
1.
1;
1'
#390
1-
18
0,
09
1*
00
17
0=
0.
0;
0'
1$
#395
15
13
1#
1!
1>
0)
02
0"
0*
11
07
1<
1/
1:
1'
#396
0$
#400
1,
19
0-
08
1+
01
16
0<
0/
0:
0'
#402
1)
12
1-
0#
0,
0+
10
1<
1*
1$
0(
#405
0*
06
1/
1;
1'
#408
0$
#410
1,
0-
1+
16
0/
0;
0'
#414
1-
0,
0+
1*
1$
#415
0*
06
1/
1;
1'
#420
1,
0-
16
1+
0/
0;
0'
0$
#425
0+
06
1.
1;
1'
#426
1$
#430
1-
0,
1*
16
0.
0;
0'
#432
1,
0-
1+
0*
0$
#435
0+
06
1.
1;
1'
#438
1$
#440
1-
0,
1*
16
0.
0;
0'
#444
1,
0-
1+
0*
0$
#445
0+
06
1.
1;
1'
#450
1-
0,
1*
16
0.
0;
0'
1$
#455
0*
06
1/
1;
1'
#456
0$
#460
1,
0-
1+
16
0/
0;
0'
#462
1-
0,
0+
1*
1$
#465
0*
06
1/
1;
1'
#468
0$
#470
1,
0-
1+
16
0/
0;
0'
#474
1-
0,
0+
1*
1$
#475
0*
06
1/
1;
1'
#480
1,
0-
16
1+
0/
0;
0'
0$
#485
0+
06
1.
1;
1'
#486
1$
#490
1-
0,
1*
16
0.
0;
0'
#492
1,
0-
1+
0*
0$
#495
0+
06
1.
1;
1'
#498
1$
#500
1-
0,
1*
16
0.
0;
0'
