testbench/includes.v
//timescale
`timescale 1ns/1ps

//defines
//`define BHVR 
`define DATA_WIDTH 8

//includes
`ifdef BHVR

`include "../d_ff_bhvr.v"
`include "../jk_ff_bhvr.v"
`include "../mux_bhvr.v"
`include "../decoder_bhvr.v"
`include "../register_bhvr.v"
`include "../counter_bhvr.v"
`include "../memory_bhvr.v"
`include "../ALU_bhvr.v"

`else //structural

`include "../d_ff.v"
`include "../jk_ff.v"
`include "../mux.v"
`include "../decoder.v"
`include "../register.v"
`include "../counter.v"
`include "../memory_bhvr.v"
`include "../ALU_components.v"
`include "../ALU.v"

`endif



//`include "../clk_divider.v"

memory_bhvr.v

module memory
 #(parameter DEPTH = 256,
 	 parameter DATA_WIDTH = `DATA_WIDTH,
	 parameter ADDR_WIDTH = $clog2(DEPTH))(

	 input [ADDR_WIDTH - 1 :0] address,
	 inout [DATA_WIDTH - 1 :0] data,
	 input CS, RD_WR,
	 input clk
);
	reg [DATA_WIDTH - 1 :0] mem [DEPTH :0] ;
	wire output_condition;
	reg [DATA_WIDTH - 1 :0] rdata;
	integer i;

	assign output_condition = CS & RD_WR;
	assign data = output_condition ? rdata : 'bz;

	initial begin
		$display("=============================================================================================");
		$display("MEMORY INITIALISED with");
		$display("DEPTH = %d, ADDRESS_WIDTH = %d, DATA_WIDTH = %d", DEPTH, ADDR_WIDTH, DATA_WIDTH);
		$display("=============================================================================================");
		$display("");
		$display("");

		//backdoor memory load task here.
		for(i = 0; i < DEPTH; i = i+1)
			mem[i] = ~0;
	end

	always @(posedge clk) begin
		if(CS) begin
			if(RD_WR) begin//READ
				rdata = mem[address];
		  end		
			else begin			//WRITE
				mem[address] = data;
			end
		end
	end

	task print_mem();
		begin
			for(i = 0; i < DEPTH; i = i+1)
				$display("mem[%d] = %h",i, mem[i]);
		end
	endtask

endmodule

testbench/memory_tb.v
`include "includes.v"

module memory_tb();
	reg clk, reset;
	wire clk_out;

	reg [addr_width - 1:0] address;
	reg CS, RD_WR;

	reg [`DATA_WIDTH - 1:0] rdata, wdata;
	wire [`DATA_WIDTH - 1:0] data_bus;
	
	reg [`DATA_WIDTH - 1:0] wdata_array[depth-1 :0];


	parameter clk_period = 10;
	reg [31:0] i;
	parameter depth = 8;
	parameter addr_width = $clog2(depth);

	always #(clk_period/2) clk = ~clk;

	//instantiate DUT
	memory #(.DEPTH(depth)) ram(.clk(clk), .address(address), .data(data_bus), .RD_WR(RD_WR), .CS(CS));

	assign data_bus = wdata;

	initial begin
		$dumpfile("memory_tb.vcd");
		$dumpvars(0,memory_tb);
		$timeformat(-9, 2, " ns", 20);

		clk <=0;
		reset <=0;
		wdata <= 'bz;
		$printtimescale;

		#13 reset = 1'b1;
	end


	initial begin
		@(posedge reset);
		#10;
		//ram.print_mem();
		
		for(i = 0; i < depth; i++) begin
			wdata_array[i] = $urandom;
			do_write(i, wdata_array[i]);
			$display("do_write at Addr %h, wdata =%h", i, wdata_array[i]);
		end
		for(i = 0; i < depth; i++) begin
			do_read(i);
			if(rdata == wdata_array[i])
				$display("PASS : data match at Addr %h, rdata = %h, wdata =%h", i, rdata, wdata_array[i]);
			else
				$display("FAIL : data mismatch at Addr %h, rdata = %h, wdata =%h", i, rdata, wdata_array[i]);
		end
		
		ram.print_mem();

		do_write('h3, 'hDE);
		#25;
		do_write('h4, 'h45);
		#36;
		do_read('h3);
			if(rdata == 'hDE)
				$display("PASS : data match at Addr %h, rdata = %h, wdata =%h", 'h3, rdata, 'hDE);
			else
				$display("FAIL : data mismatch at Addr %h, rdata = %h, wdata =%h", 'h3, rdata, 'hDE);
		

		$finish();
	end

	task do_write(input [addr_width -1:0] addr, input [`DATA_WIDTH -1:0] w_data);
		begin
			CS <= 1;
			RD_WR <= 0;
			address <= addr;
			wdata <= w_data;
			@(posedge clk);
			CS <= 0;
			wdata <= 'bz;
		end
	endtask

	//task do_read(output[`DATA_WIDTH -1:0] rdata_in);
	task do_read(input [addr_width - 1:0] addr);
		begin
			CS <=1;
			RD_WR <=1;
			address <= addr;
			@(posedge clk);
			//#(clk_period/1000);
			#1;
			rdata = data_bus;
			CS =0;
			#1;
			//#(clk_period/1000);
		end
	endtask

endmodule

testbench/memory_tb.vcd
$date
	Tue Jul 27 00:05:10 2021
$end
$version
	Icarus Verilog
$end
$timescale
	1ps
$end
$scope module memory_tb $end
$var wire 8 ! data_bus [7:0] $end
$var reg 1 " CS $end
$var reg 1 # RD_WR $end
$var reg 3 $ address [2:0] $end
$var reg 1 % clk $end
$var reg 32 & i [31:0] $end
$var reg 8 ' rdata [7:0] $end
$var reg 1 ( reset $end
$var reg 8 ) wdata [7:0] $end
$scope module ram $end
$var wire 1 " CS $end
$var wire 1 # RD_WR $end
$var wire 3 * address [2:0] $end
$var wire 1 % clk $end
$var wire 8 + data [7:0] $end
$var wire 1 , output_condition $end
$var reg 8 - rdata [7:0] $end
$var integer 32 . i [31:0] $end
$scope task print_mem $end
$upscope $end
$upscope $end
$scope task do_read $end
$var reg 3 / addr [2:0] $end
$upscope $end
$scope task do_write $end
$var reg 3 0 addr [2:0] $end
$var reg 8 1 w_data [7:0] $end
$upscope $end
$upscope $end
$enddefinitions $end
#0
$dumpvars
bx 1
bx 0
bx /
b1000 .
bx -
x,
bx +
bx *
bz )
0(
bx '
bx &
0%
bx $
x#
x"
bx !
$end
#5000
1%
#10000
0%
#13000
1(
#15000
1%
#20000
0%
#23000
b100100 !
b100100 +
0,
b100100 )
b0 $
b0 *
0#
1"
b100100 1
b0 0
b0 &
#25000
b1 $
b1 *
b10000001 !
b10000001 +
b10000001 )
1"
b10000001 1
b1 0
b1 &
1%
#30000
0%
#35000
b10 $
b10 *
b1001 !
b1001 +
b1001 )
1"
b1001 1
b10 0
b10 &
1%
#40000
0%
#45000
b11 $
b11 *
b1100011 !
b1100011 +
b1100011 )
1"
b1100011 1
b11 0
b11 &
1%
#50000
0%
#55000
b100 $
b100 *
b1101 !
b1101 +
b1101 )
1"
b1101 1
b100 0
b100 &
1%
#60000
0%
#65000
b101 $
b101 *
b10001101 !
b10001101 +
b10001101 )
1"
b10001101 1
b101 0
b101 &
1%
#70000
0%
#75000
b110 $
b110 *
b1100101 !
b1100101 +
b1100101 )
1"
b1100101 1
b110 0
b110 &
1%
#80000
0%
#85000
b111 $
b111 *
b10010 !
b10010 +
b10010 )
1"
b10010 1
b111 0
b111 &
1%
#90000
0%
#95000
1,
b0 $
b0 *
1#
bx !
bx +
bz )
1"
b0 /
b0 &
1%
#100000
0%
#105000
b100100 !
b100100 +
b100100 -
1%
#106000
bz !
bz +
0,
0"
b100100 '
#107000
b100100 !
b100100 +
1,
b1 $
b1 *
1"
b1 /
b1 &
#110000
0%
#115000
b10000001 !
b10000001 +
b10000001 -
1%
#116000
bz !
bz +
0,
0"
b10000001 '
#117000
b10000001 !
b10000001 +
1,
b10 $
b10 *
1"
b10 /
b10 &
#120000
0%
#125000
b1001 !
b1001 +
b1001 -
1%
#126000
bz !
bz +
0,
0"
b1001 '
#127000
b1001 !
b1001 +
1,
b11 $
b11 *
1"
b11 /
b11 &
#130000
0%
#135000
b1100011 !
b1100011 +
b1100011 -
1%
#136000
bz !
bz +
0,
0"
b1100011 '
#137000
b1100011 !
b1100011 +
1,
b100 $
b100 *
1"
b100 /
b100 &
#140000
0%
#145000
b1101 !
b1101 +
b1101 -
1%
#146000
bz !
bz +
0,
0"
b1101 '
#147000
b1101 !
b1101 +
1,
b101 $
b101 *
1"
b101 /
b101 &
#150000
0%
#155000
b10001101 !
b10001101 +
b10001101 -
1%
#156000
bz !
bz +
0,
0"
b10001101 '
#157000
b10001101 !
b10001101 +
1,
b110 $
b110 *
1"
b110 /
b110 &
#160000
0%
#165000
b1100101 !
b1100101 +
b1100101 -
1%
#166000
bz !
bz +
0,
0"
b1100101 '
#167000
b1100101 !
b1100101 +
1,
b111 $
b111 *
1"
b111 /
b111 &
#170000
0%
#175000
b10010 !
b10010 +
b10010 -
1%
#176000
bz !
bz +
0,
0"
b10010 '
#177000
b11011110 !
b11011110 +
b11011110 )
b11 $
b11 *
0#
1"
b11011110 1
b11 0
b1000 .
b1000 &
#180000
0%
#185000
bz !
bz +
bz )
0"
1%
#190000
0%
#195000
1%
#200000
0%
#205000
1%
#210000
b1000101 !
b1000101 +
b1000101 )
b100 $
b100 *
1"
0%
b1000101 1
b100 0
#215000
bz !
bz +
bz )
0"
1%
#220000
0%
#225000
1%
#230000
0%
#235000
1%
#240000
0%
#245000
1%
#250000
0%
#251000
b10010 !
b10010 +
1,
b11 $
b11 *
1#
1"
b11 /
#255000
b11011110 !
b11011110 +
b11011110 -
1%
#256000
bz !
bz +
0,
0"
b11011110 '
