testbench/includes.v
//timescale
`timescale 1ns/1ps

//defines
//`define BHVR 
`define DATA_WIDTH 8

//includes
`ifdef BHVR

`include "../d_ff_bhvr.v"
`include "../jk_ff_bhvr.v"
`include "../mux_bhvr.v"
`include "../decoder_bhvr.v"
`include "../register_bhvr.v"
`include "../counter_bhvr.v"
`include "../memory_bhvr.v"
`include "../ALU_bhvr.v"

`else //structural

`include "../d_ff.v"
`include "../jk_ff.v"
`include "../mux.v"
`include "../decoder.v"
`include "../register.v"
`include "../counter.v"
`include "../memory_bhvr.v"
`include "../ALU_components.v"
`include "../ALU.v"

`endif



//`include "../clk_divider.v"

mux_bhvr.v

module mux
	#(parameter DATA_WIDTH = 2,
		parameter SEL_WIDTH  = $clog2(DATA_WIDTH))(
		input [DATA_WIDTH -1:0] D,
		input [SEL_WIDTH -1:0] S,
		output Y
	);

	assign Y = D[S];

endmodule

testbench/mux_tb.v
`include "includes.v"

module mux_tb();
	reg[7:0] data;
	reg[2:0] sel;
	wire y, y1;

	mux #(.DATA_WIDTH(8)) eight_mux(.D(data),.S(sel),.Y(y));
	mux #(.DATA_WIDTH(2)) two_mux(.D(data),.S(sel),.Y(y1));

	initial begin
		$dumpfile("mux_tb.vcd");
		$dumpvars(0,mux_tb);
		$printtimescale;

		$monitor("Time = %0t \t data = %b, sel = %b, y = %b",$time, data, sel, y1);
	end

	initial begin
		for(sel = 0; sel < 7; sel = sel + 1) begin
			data = 1 << sel;
			#10;
		end
		#10;
		for(sel = 0; sel < 7; sel = sel + 1) begin
			data = 1 << sel;
			#10;
		end

		#10 $finish();
	end

endmodule

testbench/mux_tb.vcd
$date
	Tue Jul 20 00:31:18 2021
$end
$version
	Icarus Verilog
$end
$timescale
	1ps
$end
$scope module mux_tb $end
$var wire 1 ! y1 $end
$var wire 1 " y $end
$var reg 8 # data [7:0] $end
$var reg 3 $ sel [2:0] $end
$scope module eight_mux $end
$var wire 8 % D [7:0] $end
$var wire 3 & S [2:0] $end
$var wire 1 " Y $end
$upscope $end
$scope module two_mux $end
$var wire 2 ' D [1:0] $end
$var wire 1 ( S $end
$var wire 1 ! Y $end
$upscope $end
$upscope $end
$enddefinitions $end
#0
$dumpvars
0(
b1 '
b0 &
b1 %
b0 $
b1 #
1"
1!
$end
#10000
b10 '
1!
1(
b10 #
b10 %
1"
b1 $
b1 &
#20000
b0 '
0!
0(
b100 #
b100 %
1"
b10 $
b10 &
#30000
1(
b1000 #
b1000 %
1"
b11 $
b11 &
#40000
0(
b10000 #
b10000 %
1"
b100 $
b100 &
#50000
1(
b100000 #
b100000 %
1"
b101 $
b101 &
#60000
0(
b1000000 #
b1000000 %
1"
b110 $
b110 &
#70000
1(
0"
b111 $
b111 &
#80000
1!
b1 '
0(
1"
b1 #
b1 %
b0 $
b0 &
#90000
b10 '
1!
1(
b10 #
b10 %
1"
b1 $
b1 &
#100000
b0 '
0!
0(
b100 #
b100 %
1"
b10 $
b10 &
#110000
1(
b1000 #
b1000 %
1"
b11 $
b11 &
#120000
0(
b10000 #
b10000 %
1"
b100 $
b100 &
#130000
1(
b100000 #
b100000 %
1"
b101 $
b101 &
#140000
0(
b1000000 #
b1000000 %
1"
b110 $
b110 &
#150000
1(
0"
b111 $
b111 &
